squyrrel/__init__.py
squyrrel/conftest.py
squyrrel/manage.py
squyrrel/core/__init__.py
squyrrel/core/config/__init__.py
squyrrel/core/config/base.py
squyrrel/core/config/decorators.py
squyrrel/core/context/__init__.py
squyrrel/core/logging/__init__.py
squyrrel/core/logging/logger.py
squyrrel/core/logging/signals.py
squyrrel/core/logging/utils.py
squyrrel/core/registry/__init__.py
squyrrel/core/registry/config.py
squyrrel/core/registry/exception_handler.py
squyrrel/core/registry/exceptions.py
squyrrel/core/registry/logging.py
squyrrel/core/registry/meta.py
squyrrel/core/registry/nutcracker.py
squyrrel/core/registry/signals.py
squyrrel/core/signals/__init__.py
squyrrel/core/signals/base.py
squyrrel/core/utils/__init__.py
squyrrel/core/utils/paths.py
squyrrel/core/utils/singleton.py
squyrrel/db/__init__.py
squyrrel/db/connection.py
squyrrel/db/sqlite/__init__.py
squyrrel/db/sqlite/commands.py
squyrrel/db/sqlite/config.py
squyrrel/db/sqlite/connection.py
squyrrel/gui/__init__.py
squyrrel/gui/signals.py
squyrrel/gui/decorators/__init__.py
squyrrel/gui/decorators/config.py
squyrrel/gui/widgets/__init__.py
squyrrel/gui/widgets/smarttext.py
squyrrel/gui/widgets/smarttext_defaultconfig.py
squyrrel/gui/windows/__init__.py
squyrrel/gui/windows/base.py
squyrrel/ide/__init__.py
squyrrel/ide/commands.py
squyrrel/ide/gui.py
squyrrel/ide/log_window.py
squyrrel/ide/main.py
squyrrel/ide/shell.py
squyrrel/ide/shell_window.py
squyrrel/ide/windows.py
squyrrel/management/__init__.py
squyrrel/management/base.py
squyrrel/management/command_manager.py
squyrrel/management/commands.py
squyrrel/management/constants.py
squyrrel/management/context.py
squyrrel/management/exceptions.py
squyrrel/management/regtest.py
squyrrel/management/script_reader.py
squyrrel/management/signals.py
squyrrel/management/squyrrel_commands.py
squyrrel/orm/__init__.py
squyrrel/orm/commands.py
squyrrel/orm/field.py
squyrrel/orm/model.py
squyrrel/orm/signals.py
squyrrel/orm/wizzard.py
squyrrel/sql/__init__.py
squyrrel-0.1.3.dist-info/LICENSE
squyrrel-0.1.3.dist-info/METADATA
squyrrel-0.1.3.dist-info/WHEEL
squyrrel-0.1.3.dist-info/top_level.txt
squyrrel-0.1.3.dist-info/RECORD
